MANIFEST.in
requirements-test.txt
requirements.txt
setup.py
debian/changelog
debian/compat
debian/control
debian/python-upaas-admin.dirs
debian/python-upaas-admin.install
debian/python-upaas-admin.postinst
debian/python-upaas-admin.preinst
debian/rules
debian/source/format
upaas_admin/__init__.py
upaas_admin/config.py
upaas_admin/upaas_admin
upaas_admin/urls.py
upaas_admin.egg-info/PKG-INFO
upaas_admin.egg-info/SOURCES.txt
upaas_admin.egg-info/dependency_links.txt
upaas_admin.egg-info/requires.txt
upaas_admin.egg-info/top_level.txt
upaas_admin/apps/__init__.py
upaas_admin/apps/admin/__init__.py
upaas_admin/apps/admin/forms.py
upaas_admin/apps/admin/urls.py
upaas_admin/apps/admin/views.py
upaas_admin/apps/admin/management/__init__.py
upaas_admin/apps/admin/management/commands/__init__.py
upaas_admin/apps/admin/management/commands/create_indexes.py
upaas_admin/apps/admin/management/commands/migrate_db.py
upaas_admin/apps/applications/__init__.py
upaas_admin/apps/applications/api.py
upaas_admin/apps/applications/constants.py
upaas_admin/apps/applications/exceptions.py
upaas_admin/apps/applications/forms.py
upaas_admin/apps/applications/helpers.py
upaas_admin/apps/applications/http.py
upaas_admin/apps/applications/mixin.py
upaas_admin/apps/applications/models.py
upaas_admin/apps/applications/urls.py
upaas_admin/apps/applications/views.py
upaas_admin/apps/scheduler/__init__.py
upaas_admin/apps/scheduler/api.py
upaas_admin/apps/scheduler/base.py
upaas_admin/apps/scheduler/forms.py
upaas_admin/apps/scheduler/models.py
upaas_admin/apps/servers/__init__.py
upaas_admin/apps/servers/api.py
upaas_admin/apps/servers/models.py
upaas_admin/apps/tasks/__init__.py
upaas_admin/apps/tasks/api.py
upaas_admin/apps/tasks/constants.py
upaas_admin/apps/tasks/models.py
upaas_admin/apps/tasks/mule.py
upaas_admin/apps/tasks/management/__init__.py
upaas_admin/apps/tasks/management/commands/__init__.py
upaas_admin/apps/tasks/management/commands/bootstrap_os_image.py
upaas_admin/apps/tasks/management/commands/mule_backend.py
upaas_admin/apps/tasks/management/commands/mule_builder.py
upaas_admin/apps/users/__init__.py
upaas_admin/apps/users/forms.py
