Metadata-Version: 1.0
Name: upaas-admin
Version: 0.3.1
Summary: UPaaS admin API and UI
Home-page: UNKNOWN
Author: Łukasz Mierzwa
Author-email: l.mierzwa@gmail.com
License: GPLv3
Platform: UNKNOWN
